refract_mlflow_plugin/__init__.py
refract_mlflow_plugin/app.py
refract_mlflow_plugin/request_header_provider.py
refract_mlflow_plugin-1.0.3.dist-info/LICENSE
refract_mlflow_plugin-1.0.3.dist-info/METADATA
refract_mlflow_plugin-1.0.3.dist-info/WHEEL
refract_mlflow_plugin-1.0.3.dist-info/entry_points.txt
refract_mlflow_plugin-1.0.3.dist-info/top_level.txt
refract_mlflow_plugin-1.0.3.dist-info/RECORD
