Metadata-Version: 2.1
Name: refract-mlflow-plugin
Version: 1.0.3
Summary: Refract plugin for MLflow
Home-page: UNKNOWN
License: UNKNOWN
Platform: UNKNOWN
License-File: LICENSE
Requires-Dist: mlflow ==2.10.0
